ridge/__init__.py
ridge/plotting.py
ridge/utils.py
pyridge-0.1.0.dist-info/LICENSE
pyridge-0.1.0.dist-info/METADATA
pyridge-0.1.0.dist-info/WHEEL
pyridge-0.1.0.dist-info/top_level.txt
pyridge-0.1.0.dist-info/RECORD
