Metadata-Version: 2.1
Name: pyridge
Version: 0.1.0
Summary: Efficient grid-based evaluation of probability distributions
Author-email: Chris Bowman <chris.bowman.physics@gmail.com>
License: MIT License
Project-URL: Homepage, https://github.com/C-bowman/ridge
Classifier: Programming Language :: Python :: 3
Classifier: License :: OSI Approved :: MIT License
Classifier: Operating System :: OS Independent
Requires-Python: >=3.9
License-File: LICENSE
Requires-Dist: numpy >=1.20
Requires-Dist: scipy >=1.6.3
Requires-Dist: matplotlib >=3.4.2
Provides-Extra: tests
Requires-Dist: pytest >=3.3.0 ; extra == 'tests'
Requires-Dist: pytest-cov >=3.0.0 ; extra == 'tests'
